revseqs/__init__.py
revseqs/__main__.py
revseqs/revseqs.py
rev_seqs-0.0.1.dist-info/LICENSE.txt
rev_seqs-0.0.1.dist-info/METADATA
rev_seqs-0.0.1.dist-info/WHEEL
rev_seqs-0.0.1.dist-info/top_level.txt
rev_seqs-0.0.1.dist-info/RECORD
