Metadata-Version: 2.1
Name: rev-seqs
Version: 0.0.1
Summary: Revert sequences to consensus
Home-page: https://github.com/nguyen-t-nhan/rev-seqs
Author: Nhan Nguyen
Author-email: nhannguyen72089@gmail.com
License: UNKNOWN
Platform: UNKNOWN
Classifier: Programming Language :: Python :: 3
Classifier: License :: OSI Approved :: MIT License
Classifier: Operating System :: OS Independent
Requires-Python: >=3.6
Requires-Dist: numpy
Requires-Dist: pandas
Requires-Dist: pysam
